[
        {
		//nations
		"name": "4044",
		"leaderName": "GR1M",
		"adjective": ["4044"],
		"startBias": ["Hill"],
		"preferredVictoryType": "Domination",

		"startIntroPart1": "ERROR MACRO.",
		"startIntroPart2": "",

		"declaringWar": "xxxcccccxx",
		"attacked": "mmmxccc xxcccc.",
		"defeated": "ERROR ERROR ERROR ERROR ERROR.",
		"introduction": "EV3N THE D4RK3ST N1GHT WILL 3ND AND TH3 5UN W1LL R1S3",

		"neutralHello": "XXCCCX CCCCXXX.",
		"hateHello": "ERROR ERROR ERROR ERROR ERROR",

		"tradeRequest": "XCCXX CCCXXXXX.",
                "uniqueName": "50055",
                "uniques": ["[Gold] cost of purchasing [All] units [-30]%","[+10]% Production when constructing [Military] units [in all cities]","[+1 Faith] [in all cities]"],

		"outerColor": [3, 3, 3],
		"innerColor": [214, 210, 210],
		"cities": ["10449","Arat","Prime",
			"Federal",
			"United","Arkistia","Obeliskia","Techtia",
			"Generations","Dogmatic"],
        "spyNames": ["Sir Charles"]
	},
        {
		//nations
		"name": "Imperio da Grandeza",
		"leaderName": "Sophia",
		"adjective": ["Brasilians"],
		"startBias": ["Jungle"],
		"preferredVictoryType": "Ascension",

		"startIntroPart1": "Sophia achieved the rebirth of an entire destroyed nation, Irma tried to defame her actions and in response, Sophia managed to find a way to take advantage of scarce resources in transcendence.",
		"startIntroPart2": "",

		"declaringWar": "This is the end!",
		"attacked": "Oh, so you are attacking us.",
		"defeated": "You can continue your reign? im sure you won´t.",
		"introduction": "Greetings",

		"neutralHello": "Greetings.",
		"hateHello": "What do YOU want?!",

		"tradeRequest": "It appears that you do have a reason for existing – to make this deal with me.",
                "uniqueName": "Reino da beleza e da Arte",
                "uniques": ["[+2 Culture] from every [Jungle]", "[+1 Science] from every [Lakes]"],

		"outerColor": [33, 33, 31],
		"innerColor": [252, 219, 111],
		"cities": ["Brasilia","Arat","Prime",
			"Federal",
			"United","Arkistia","Obeliskia","Techtia",
			"Generations","Dogmatic"],
        "spyNames": ["Sir Charles"]
	},
        {
		//nations
		"name": "Cryogenic Empire",
		"leaderName": "Juliana",
		"adjective": ["Cryogenic"],
		"startBias": ["Snow"],
		"preferredVictoryType": "Domination",

		"startIntroPart1": "The cryogenic empire appeared in very distant areas in the cosmos, the homodeus sought new ways to dominate the world, and found new beasts and new challenges.",
		"startIntroPart2": "",

		"declaringWar": "This is the end!",
		"attacked": "Oh, so you are attacking us.",
		"defeated": "You can continue your reign? im sure you won´t.",
		"introduction": "Greetings",

		"neutralHello": "Greetings.",
		"hateHello": "What do YOU want?!",

		"tradeRequest": "It appears that you do have a reason for existing – to make this deal with me.",
                "uniqueName": "Arctic Flower",
                "uniques": ["[+2 Faith] from each [Trade route]", "Allied City-States provide [Science] equal to [20]% of what they produce for themselves"],

		"outerColor": [202, 247, 250],
		"innerColor": [8, 60, 64],
		"cities": ["Snowflake","Arat","Prime",
			"Federal",
			"United","Arkistia","Obeliskia","Techtia",
			"Generations","Dogmatic"],
        "spyNames": ["Sir Charles"]
	},
        {
		//nations
		"name": "Volcanic Nation",
		"leaderName": "Aleid",
		"adjective": ["Volcanic"],
		"startBias": ["Volcano"],
		"preferredVictoryType": "Domination",

		"startIntroPart1": "The Fire consumes Everything.",
		"startIntroPart2": "",

		"declaringWar": "This is the end!",
		"attacked": "Oh, so you are attacking us.",
		"defeated": "You can continue your reign? im sure you won´t.",
		"introduction": "Greetings",

		"neutralHello": "Greetings.",
		"hateHello": "What do YOU want?!",

		"tradeRequest": "It appears that you do have a reason for existing – to make this deal with me.",
                "uniqueName": "Consumption Force",
                "uniques": ["[+4 Faith] from every [Volcano]", "[+1 Food] from every [Volcanic Soil]"],

		"outerColor": [82, 43, 38],
		"innerColor": [240, 55, 31],
		"cities": ["Infernum","Arat","Prime",
			"Federal",
			"United","Arkistia","Obeliskia","Techtia",
			"Generations","Dogmatic"],
        "spyNames": ["Sir Charles"]
	},
        {
		//nations
		"name": "Dormanta Imperios",
		"leaderName": "Micaela",
		"adjective": ["Dormanta"],
		"startBias": ["Redwoods"],
		"preferredVictoryType": "Domination",

		"startIntroPart1": "In the heart of nature, where the sun barely peeks out, lies a dream forest.",
		"startIntroPart2": "",

		"declaringWar": "This is the end!",
		"attacked": "Oh, so you are attacking us.",
		"defeated": "You can continue your reign? im sure you won´t.",
		"introduction": "Greetings",

		"neutralHello": "Greetings.",
		"hateHello": "What do YOU want?!",

		"tradeRequest": "It appears that you do have a reason for existing – to make this deal with me.",
                "uniqueName": "Arbara Animos",
                "uniques": ["[+1 Production] from every [Redwoods]", "[+1 Food] from every [Sap Collector]","[-5]% Culture cost of adopting new Policies"],

		"outerColor": [73, 74, 70],
		"innerColor": [236, 252, 169],
		"cities": ["Si Alia","Arat","Prime",
			"Federal",
			"United","Arkistia","Obeliskia","Techtia",
			"Generations","Dogmatic"],
        "spyNames": ["Sir Charles"]
	},
        {
		"name": "Smierc",
		"leaderName": "Karina",
		"adjective": ["Polish"],
		"startBias": ["Tundra"],
		"preferredVictoryType": "Domination",

		"startIntroPart1": "In the heart of nature, where the sun barely peeks out, lies a dream forest.",
		"startIntroPart2": "",

		"declaringWar": "This is the end!",
		"attacked": "Oh, so you are attacking us.",
		"defeated": "You can continue your reign? im sure you won´t.",
		"introduction": "Greetings",

		"neutralHello": "Greetings.",
		"hateHello": "What do YOU want?!",

		"tradeRequest": "It appears that you do have a reason for existing – to make this deal with me.",
                "uniqueName": "Wiersze Bólu",
                "uniques": ["[+20]% Production when constructing [Prey] units [in all cities]","[+20]% Production when constructing [Flying] units [in all cities]","[+15]% Production when constructing [Destroyer of Theropods] units [in all cities]"],

		"outerColor": [232, 202, 162],
		"innerColor": [74, 14, 43],
		"cities": ["Kapitał Sakramentalny","Arat","Prime",
			"Federal",
			"United","Arkistia","Obeliskia","Techtia",
			"Generations","Dogmatic"],
        "spyNames": ["Sir Charles"]
	},
	{
		//nations
		"name": "Merveilleuse Commande",
		"leaderName": "Brigitte",
		"adjective": ["French"],
		"startBias": ["Coast"],
		"preferredVictoryType": "Ascension",

		"startIntroPart1": "Brigitte led her own civilization after revolutionizing Irma's military government, the order was based on scientific destruction and glorifying cultural values, but that made Sophia stop supporting her, and now they were almost opposite poles, but with the same feeling, against Irma",
		"startIntroPart2": "",

		"declaringWar": "This is the end!",
		"attacked": "Oh, so you are attacking us.",
		"defeated": "You can continue your reign? im sure you won´t.",
		"introduction": "Greetings",

		"neutralHello": "Greetings.",
		"hateHello": "What do YOU want?!",

		"tradeRequest": "It appears that you do have a reason for existing – to make this deal with me.",
                "uniqueName": "Grande est la nouvelle France",
                "uniques": ["[+1 Culture] [in all cities]", "[+1 Food] from every [Luxury resource]", "[+1 Faith] from every [Wonder]"],

		"outerColor": [50, 20, 60],
		"innerColor": [210, 100, 200],
		"cities": ["Paris","Arat","Prime",
			"Federal",
			"United","Arkistia","Obeliskia","Techtia",
			"Generations","Dogmatic"],
        "spyNames": ["Sir Charles"]
	},
        {
		"name": "Imperial America",
		"leaderName": "Evolet",
		"adjective": ["America"],
		"startBias": ["Hill"],
		"preferredVictoryType": "Ascension",

		"startIntroPart1": "America had no one to turn to, except for a strange teenage daughter of an aristocratic family, Evolet, she imposed taxes, sought to recover her country fiscally, replaced the shotguns, and brought in the nuclear industry, with selfish interests, she also seeks to stop Irma, since Evolet plans to dominate the world too",
		"startIntroPart2": "",

		"declaringWar": "This is the end!",
		"attacked": "Oh, so you are attacking us.",
		"defeated": "You can continue your reign? im sure you won´t.",
		"introduction": "Greetings",

		"neutralHello": "Greetings.",
		"hateHello": "What do YOU want?!",

		"tradeRequest": "It appears that you do have a reason for existing – to make this deal with me.",
                "uniqueName": "Freedom",
                "uniques": ["[+1 Gold] from every [Ark Monument]", "[+1 Happiness] from every [Ark Monument]", "[-2 Gold] from every [Place Mark]"],

		"outerColor": [63, 105, 242],
		"innerColor": [198, 209, 247],
		"cities": ["Washington","Arat","Prime",
			"Federal",
			"United","Arkistia","Obeliskia","Techtia",
			"Generations","Dogmatic"],
        "spyNames": ["Sir Charles"]
	}
        {
		"name": "Germania",
		"leaderName": "Irma",
		"adjective": ["Germany"],
		"startBias": ["Tundra"],
		"preferredVictoryType": "Ascension",

		"startIntroPart1": "It was a dark night in the Tek era when that woman in a dark uniform appears in Germany. No one knows how she came to power, but she clung to it, she radicalized quickly, she brought with her the technologies of transcendence, but she destroyed the culture and faith of She filled her own nation with hatred, or as she calls it, Ich Asse policies, but who are they to stop her and her ambition? now that she expands her borders in the Arks",
		"startIntroPart2": "",

		"declaringWar": "This is the end!",
		"attacked": "Oh, so you are attacking us.",
		"defeated": "You can continue your reign? im sure you won´t.",
		"introduction": "Greetings",

		"neutralHello": "Greetings.",
		"hateHello": "What do YOU want?!",

		"tradeRequest": "It appears that you do have a reason for existing – to make this deal with me.",
                "uniqueName": "Neues Reich",
                "uniques": ["[+15]% of excess happiness converted to [Production]", "[+25]% [Production] [in all cities] <when at war>", "[-70]% [Culture] [in all cities] <when at war>", "[+5]% [Science] [in all cities] <when at war>", "[-100]% [Faith] [in all cities] <when at war>"],

		"outerColor": [31, 29, 29],
		"innerColor": [217, 4, 4],
		"cities": ["Germania","Arat","Prime",
			"Federal",
			"United","Arkistia","Obeliskia","Techtia",
			"Generations","Dogmatic"],
        "spyNames": ["Sir Charles"]
	}
        {
		"name": "Alwahid hu Alsahih",
		"leaderName": "Mehmet",
		"adjective": ["Arab"],
		"startBias": ["Desert"],
		"preferredVictoryType": "Ascension",

		"startIntroPart1": "Imagine not being able to fall into the seduction of the corruption of the mandate, that happened to Mehmet, faithful to the culture, he maintained the faith and allied the mosque with military science, and seeks to stop Irma, since she plans to destroy his religion, and committed multiple genocides against his people.",
		"startIntroPart2": "",

		"declaringWar": "This is the end!",
		"attacked": "Oh, so you are attacking us.",
		"defeated": "You can continue your reign? im sure you won´t.",
		"introduction": "Greetings",

		"neutralHello": "Greetings.",
		"hateHello": "What do YOU want?!",

		"tradeRequest": "It appears that you do have a reason for existing – to make this deal with me.",
                "uniqueName": "Barakak Allah",
                "uniques": ["[+1 Faith] from every [Bonus resource]", "[+1 Production] from every [Rockwell Stories]", "[+1 Gold] from every [Desert]"],

		"outerColor": [22, 54, 12],
		"innerColor": [88, 201, 52],
		"cities": ["Almuqadasa","Arat","Prime",
			"Federal",
			"United","Arkistia","Obeliskia","Techtia",
			"Generations","Dogmatic"],
        "spyNames": ["Sir Charles"]
	}
        {
		"name": "Sunken",
		"leaderName": "Hafsa",
		"adjective": ["Sunken"],
		"startBias": ["Sunken Land"],
		"preferredVictoryType": "Ascension",

		"startIntroPart1": "Hafsa is Mehmet's sister, Irma invested in the modernization of her town, and slowly corrupted her into an android with barely a human heart, her mind was not normal either, it was now a set of automated processes, Mehmet ended up abandoning her, but She continued on her path, and now she wants to kill almost everyone, and turn the Arks into a world dominated by androids.",
		"startIntroPart2": "",

		"declaringWar": "This is the end!",
		"attacked": "Oh, so you are attacking us.",
		"defeated": "You can continue your reign? im sure you won´t.",
		"introduction": "Greetings",

		"neutralHello": "Greetings.",
		"hateHello": "What do YOU want?!",

		"tradeRequest": "It appears that you do have a reason for existing – to make this deal with me.",
                "uniqueName": "Afkar Jadida",
                "uniques": ["[+1 Food] from every [Coast]", "[+2 Culture] from every [First Armory]"],

		"outerColor": [96, 150, 129],
		"innerColor": [45, 64, 57],
		"cities": ["Mylie","Arat","Prime",
			"Federal",
			"United","Arkistia","Obeliskia","Techtia",
			"Generations","Dogmatic"],
        "spyNames": ["Sir Charles"]
	}
        {
		"name": "Spiras Foria",
		"leaderName": "Mila",
		"adjective": ["Autumn"],
		"startBias": ["Forest"],
		"preferredVictoryType": "Ascension",

		"startIntroPart1": "Mila was a young woman who was born in the autumn forests, so much was her fascination that she performed an operation by cutting lianas into her tissue, forcing a mutation to transform into the new mother earth, the majority of botanists were consumed by her song through the temperate forests, drags them towards madness, and the only thing that is written in the telegrams is Spiras Foria",
		"startIntroPart2": "",

		"declaringWar": "This is the end!",
		"attacked": "Oh, so you are attacking us.",
		"defeated": "You can continue your reign? im sure you won´t.",
		"introduction": "Greetings",

		"neutralHello": "Greetings.",
		"hateHello": "What do YOU want?!",

		"tradeRequest": "It appears that you do have a reason for existing – to make this deal with me.",
                "uniqueName": "Afkar Jadida",
                "uniques": ["[+1 Production] from every [Forest] and [Jungle]", "[+1 Food] from every [2] [Forest] and [Jungle]", "[+1 Production] from every [Lumber mill]"],

		"outerColor": [84, 13, 3],
		"innerColor": [252, 116, 5],
		"cities": ["Tiperrary","Arat","Prime",
			"Federal",
			"United","Arkistia","Obeliskia","Techtia",
			"Generations","Dogmatic"],
        "spyNames": ["Sir Charles"]
	}
        {
		"name": "Zare",
		"leaderName": "Anezka",
		"adjective": ["Zare"],
		"startBias": ["Jungle"],
		"preferredVictoryType": "Ascension",

		"startIntroPart1": "Anezka appeared, said in ancient europe, but the stone writtings travelled beyond what we know, or what we dont know, ancient europe might be dead, but we still have Anezka",
		"startIntroPart2": "",

		"declaringWar": "This is the end!",
		"attacked": "Oh, so you are attacking us.",
		"defeated": "You can continue your reign? im sure you won´t.",
		"introduction": "Greetings",

		"neutralHello": "Greetings.",
		"hateHello": "What do YOU want?!",

		"tradeRequest": "It appears that you do have a reason for existing – to make this deal with me.",
                "uniqueName": "Byt znovuzrozen",
                "uniques": ["[+1 Science] from every [5] [Faith] and [Culture]", "[+1 Science] from every [Great Improvement]"],

		"outerColor": [81, 214, 168],
		"innerColor": [3, 41, 107],
		"cities": ["Zemrit","Arat","Prime",
			"Federal",
			"United","Arkistia","Obeliskia","Techtia",
			"Generations","Dogmatic"],
        "spyNames": ["Sir Charles"]
	},
        {
		"name": "Reef Kings",
		"leaderName": "Candela",
		"adjective": ["Reefers"],
		"startBias": ["Swamp Zone"],
		"preferredVictoryType": "Ascension",

		"startIntroPart1": "The Reef Kings were the biggest threats on the Arks oceans, the leaders of the civilization were so strong they actually managed to trascend into the biggest empires, but a friend of Germania.",
		"startIntroPart2": "",

		"declaringWar": "This is the end!",
		"attacked": "Oh, so you are attacking us.",
		"defeated": "You can continue your reign? im sure you won´t.",
		"introduction": "Greetings",

		"neutralHello": "Greetings.",
		"hateHello": "What do YOU want?!",

		"tradeRequest": "It appears that you do have a reason for existing – to make this deal with me.",
                "uniqueName": "Coast Fighters",
                "uniques": ["[+15]% Strength <when fighting in [Coast] tiles>", "[+15]% Strength <when fighting in [Swamp Zone] tiles>", "[+1 Gold] from every [Coast]", "Double quantity of [Coral] produced", "Double quantity of [Black Pearl] produced"],

		"outerColor": [51, 14, 34],
		"innerColor": [247, 156, 205],
		"cities": ["Life","Arat","Prime",
			"Federal",
			"United","Arkistia","Obeliskia","Techtia",
			"Generations","Dogmatic"],
        "spyNames": ["Sir Charles"]
	},
        {
		"name": "East People",
		"leaderName": "Margaret",
		"adjective": ["East People"],
		"startBias": ["Tundra"],
		"preferredVictoryType": "Ascension",

		"startIntroPart1": "Irma was born on the Birmountia lands, before going insane with Germania project, this people have not died yet, Margaret seems to bring light to their lives",
		"startIntroPart2": "",

		"declaringWar": "This is the end!",
		"attacked": "Oh, so you are attacking us.",
		"defeated": "You can continue your reign? im sure you won´t.",
		"introduction": "Greetings",

		"neutralHello": "Greetings.",
		"hateHello": "What do YOU want?!",

		"tradeRequest": "It appears that you do have a reason for existing – to make this deal with me.",
                "uniqueName": "Against Germania",
                "uniques": ["[+5]% Production when constructing [Chariot] units [in all cities]", "[+1 Production] from every [3] [Mine]", "Double quantity of [Heart of the Shadows] produced", "[+10]% Strength for cities"],

		"outerColor": [49, 0, 105],
		"innerColor": [252, 136, 161],
		"cities": ["Birmountia","Arat","Prime",
			"Federal",
			"United","Arkistia","Obeliskia","Techtia",
			"Generations","Dogmatic"],
        "spyNames": ["Sir Charles"]
	}
        {
		"name": "Mulkin Zafi",
		"leaderName": "King Umbi",
		"adjective": ["Zafians"],
		"startBias": ["Desert"],
		"preferredVictoryType": "Domination",

		"startIntroPart1": "Mulkin Zafi was one of the people that didnt believe Nosti people back on Scorched Earth, Irma didnt expect these people to trascend, but they did, and now they can destroy big tribes without any difficult, and they often defeat her on Irma´s nightmares.",
		"startIntroPart2": "",

		"declaringWar": "This is the end!",
		"attacked": "Oh, so you are attacking us.",
		"defeated": "You can continue your reign? im sure you won´t.",
		"introduction": "Greetings",

		"neutralHello": "Greetings.",
		"hateHello": "What do YOU want?!",

		"tradeRequest": "It appears that you do have a reason for existing – to make this deal with me.",
                "uniqueName": "Ma Aikata",
                "uniques": ["[+10]% Production when constructing [Civilian] units for cities on [Desert] tiles", "[+1 Science] from every [2] [Marble Statue]", "[+10]% Strength for cities on [Desert] tiles"],

		"outerColor": [252, 186, 3],
		"innerColor": [99, 10, 0],
		"cities": ["Zafmu","Arat","Prime",
			"Federal",
			"United","Arkistia","Obeliskia","Techtia",
			"Generations","Dogmatic"],
        "spyNames": ["Sir Charles"]
	}
        {
		"name": "New Mongolia",
		"leaderName": "Ajilchid Khan",
		"adjective": ["Mongolians"],
		"startBias": ["Tundra"],
		"preferredVictoryType": "Domination",

		"startIntroPart1": "Even the coldest people found peace on this new place, but they have the urge to kill, to invade, now they have a lot of potential, might this time be their ultimate win?.",
		"startIntroPart2": "",

		"declaringWar": "This is the end!",
		"attacked": "Oh, so you are attacking us.",
		"defeated": "You can continue your reign? im sure you won´t.",
		"introduction": "Greetings",

		"neutralHello": "Greetings.",
		"hateHello": "What do YOU want?!",

		"tradeRequest": "It appears that you do have a reason for existing – to make this deal with me.",
                "uniqueName": "Urdu Legacy",
                "uniques": ["[+20]% of excess happiness converted to [Culture]", "[+15]% Strength <for [Mounted] units> on [Tundra] or [Snow] tiles"],
                
                "outerColor": [179, 178, 184],
		"innerColor": [37, 43, 33],
		"cities": ["Ulan Bator","Arat","Prime",
			"Federal",
			"United","Arkistia","Obeliskia","Techtia",
			"Generations","Dogmatic"],
        "spyNames": ["Sir Charles"]
	},
        {
		"name": "Swamp Republic",
		"leaderName": "Morrison",
		"adjective": ["Swampers"],
		"startBias": ["Swamp Zone"],
		"preferredVictoryType": "Domination",

		"startIntroPart1": "The swamps were almost deleted by Irma, but some people did actually develop civilization on places were Swamps were as common as Grasslands or Plains, those people are the Swamp Republic, Morrison wants to end the monarchy system a lot of leaders have been using until now, he will win?.",
		"startIntroPart2": "",

		"declaringWar": "This is the end!",
		"attacked": "Oh, so you are attacking us.",
		"defeated": "You can continue your reign? im sure you won´t.",
		"introduction": "Greetings",

		"neutralHello": "Greetings.",
		"hateHello": "What do YOU want?!",

		"tradeRequest": "It appears that you do have a reason for existing – to make this deal with me.",
                "uniqueName": "Marsh Popular Democrats",
                "uniques": ["[+15]% Strength <for [Mounted] units> on [Swamp Zone]", "[+2 Production] from every [Swamp Zone]", "[+2 Food] from every [Marsh]"],
                
                "outerColor": [247, 155, 79],
		"innerColor": [3, 12, 107],
		"cities": ["Democrats Place","Arat","Prime",
			"Federal",
			"United","Arkistia","Obeliskia","Techtia",
			"Generations","Dogmatic"],
        "spyNames": ["Sir Charles"]
	},
        {
		"name": "Radical Feminism Society",
		"leaderName": "Anxn",
		"adjective": ["Radical Feminists"],
		"startBias": ["Tundra"],
		"preferredVictoryType": "Domination",

		"startIntroPart1": "Irma searched the most radical people for join her cause, what she found? Anxn, a person that represents a tiny portion of the American Empire, now she will... win?.",
		"startIntroPart2": "",

		"declaringWar": "This is the end!",
		"attacked": "Oh, so you are attacking us.",
		"defeated": "You can continue your reign? im sure you won´t.",
		"introduction": "Greetings",

		"neutralHello": "Greetings.",
		"hateHello": "What do YOU want?!",

		"tradeRequest": "It appears that you do have a reason for existing – to make this deal with me.",
                "uniqueName": "Irma Lover",
                "uniques": ["[+15]% Culture [in all cities]", "[-15]% Faith [in all cities]", "[+25]% [Culture] [in all cities] <when at war>"],
                
                "outerColor": [242, 219, 255],
		"innerColor": [185, 78, 242],
		"cities": ["Rights","Arat","Prime",
			"Federal",
			"United","Arkistia","Obeliskia","Techtia",
			"Generations","Dogmatic"],
        "spyNames": ["Sir Charles"]
	}
        {
		"name": "Male Supremacy Group",
		"leaderName": "Commander Mithen",
		"adjective": ["Supremacy Males"],
		"startBias": ["Snow"],
		"preferredVictoryType": "Domination",

		"startIntroPart1": "Irma searched the most radical people for join her cause, what she found? Anxn, a person that represents a tiny portion of the American Empire, now she will... win?.",
		"startIntroPart2": "",

		"declaringWar": "This is the end!",
		"attacked": "Oh, so you are attacking us.",
		"defeated": "You can continue your reign? im sure you won´t.",
		"introduction": "Greetings",

		"neutralHello": "Greetings.",
		"hateHello": "What do YOU want?!",

		"tradeRequest": "It appears that you do have a reason for existing – to make this deal with me.",
                "uniqueName": "Teufelslied",
                "uniques": ["[+20]% XP gained from combat <for [Military] units>", "[+15]% Production [in all cities]"],
                
                "outerColor": [171, 17, 0],
		"innerColor": [48, 20, 17],
		"cities": ["Mankind","Arat","Prime",
			"Federal",
			"United","Arkistia","Obeliskia","Techtia",
			"Generations","Dogmatic"],
        "spyNames": ["Sir Charles"]
	}
        {
		"name": "Communism Republic",
		"leaderName": "General Shchors",
		"adjective": ["Communist"],
		"startBias": ["Snow"],
		"preferredVictoryType": "Domination",

		"startIntroPart1": "Irma feared the snow men, that have kind of weird ideas of how the world shoul work, lets see if they can win this match.",
		"startIntroPart2": "",

		"declaringWar": "This is the end!",
		"attacked": "Oh, so you are attacking us.",
		"defeated": "You can continue your reign? im sure you won´t.",
		"introduction": "Greetings",

		"neutralHello": "Greetings.",
		"hateHello": "What do YOU want?!",

		"tradeRequest": "It appears that you do have a reason for existing – to make this deal with me.",
                "uniqueName": "Stalin Legacy",
                "uniques": ["[+20]% of excess happiness converted to [Production]", "[+20]% of excess happiness converted to [Science]", "[+5]% Science [in all cities]"],
                
                "outerColor": [250, 207, 202],
		"innerColor": [48, 20, 17],
		"cities": ["Aratkia","Arat","Prime",
			"Federal",
			"United","Arkistia","Obeliskia","Techtia",
			"Generations","Dogmatic"],
        "spyNames": ["Sir Charles"]
	}
        {
		"name": "Fililpino Throne",
		"leaderName": "Kudarat IV",
		"adjective": ["Fililpino"],
		"startBias": ["Coast"],
		"preferredVictoryType": "Domination",

		"startIntroPart1": "During some of the travels on the Arks, Sophia founded Kudarat on some distanct shores, with a lot of city states and forts, those people had some power over faith, that no one could match.",
		"startIntroPart2": "",

		"declaringWar": "This is the end!",
		"attacked": "Oh, so you are attacking us.",
		"defeated": "You can continue your reign? im sure you won´t.",
		"introduction": "Greetings",

		"neutralHello": "Greetings.",
		"hateHello": "What do YOU want?!",

		"tradeRequest": "It appears that you do have a reason for existing – to make this deal with me.",
                "uniqueName": "Helper of the Faith",
                "uniques": ["[+40% Faith] from City-States", "[+1 Faith] from every [2] [Wooden Fort]",
"[+2 Faith] from every [Cement Works]",
"[+2 Faith] from every [Stone Fort]",
"[+3 Faith] from every [Metal Fort]",
"[+3 Faith] from every [Tek Forcefields]",
"[+4 Faith] from every [Tek Protector]",
"[+5 Faith] from every [Tek Armor Fabricator]" ],
                
                "outerColor": [61, 71, 21],
		"innerColor": [32, 252, 3],
		"cities": ["Agenda","Arat","Prime",
			"Federal",
			"United","Arkistia","Obeliskia","Techtia",
			"Generations","Dogmatic"],
        "spyNames": ["Sir Charles"]
	},
        {
		"name": "Armenia Illumination",
		"leaderName": "Tiridates XI",
		"adjective": ["Armenian"],
		"startBias": ["Hill"],
		"preferredVictoryType": "Domination",

		"startIntroPart1": "The Armenians mourned their loss and made a monument where they kept their bones and footprints and dedicated an eternal poem to them, while other groups sought to end all kinds of memory..",
		"startIntroPart2": "",

		"declaringWar": "This is the end!",
		"attacked": "Oh, so you are attacking us.",
		"defeated": "You can continue your reign? im sure you won´t.",
		"introduction": "Greetings",

		"neutralHello": "Greetings.",
		"hateHello": "What do YOU want?!",

		"tradeRequest": "It appears that you do have a reason for existing – to make this deal with me.",
                "uniqueName": "The Illumination of Tiridates",
                "uniques": ["[+1 Faith] from every [Hill]"],
                
                "outerColor": [168, 47, 116],
		"innerColor": [255, 219, 120],
		"cities": ["Tigrana shat","Arat","Prime",
			"Federal",
			"United","Arkistia","Obeliskia","Techtia",
			"Generations","Dogmatic"],
        "spyNames": ["Sir Charles"]
	}
        {
		"name": "Mega Korea",
		"leaderName": "Sun Ultra",
		"adjective": ["Korean"],
		"startBias": ["Coast"],
		"preferredVictoryType": "Domination",

		"startIntroPart1": "Korea was meant to be this big? it seems so",
		"startIntroPart2": "",

		"declaringWar": "This is the end!",
		"attacked": "Oh, so you are attacking us.",
		"defeated": "You can continue your reign? im sure you won´t.",
		"introduction": "Greetings",

		"neutralHello": "Greetings.",
		"hateHello": "What do YOU want?!",

		"tradeRequest": "It appears that you do have a reason for existing – to make this deal with me.",
                "uniqueName": "Turtle Ships",
                "uniques": ["[+10]% Production when constructing [Water Melee] units [in all cities]","[+1 Science] from every [3] [Coast]", "[+1 Science] from every [2] [Ark Monument]", "[+10]% Production when constructing [Civilian] units [in all cities]"],

		"outerColor": [73, 39, 245],
		"innerColor": [10, 10, 10],
		"cities": ["Seoul","Arat","Prime",
			"Federal",
			"United","Arkistia","Obeliskia","Techtia",
			"Generations","Dogmatic"],
        "spyNames": ["Sir Charles"]
	}
]
